{
  "id": "nie-x87e.12",
  "title": "Bob scan timeout swallows scan_to_tip errors as panics",
  "description": "In e2e_testnet.rs lines 489-493, the Bob scan runs inside a timeout with an inner .expect() on scan_to_tip(). If scan_to_tip() returns Err, the inner .expect() panics inside the async block. That panic propagates as a task panic rather than a clean test failure, obscuring the actual scan error. Fix: pass scan_to_tip() directly to timeout() and chain the two .expect() calls at the call site, which keeps the Elapsed case and the scan error case distinct and produces readable output for both.",
  "status": "closed",
  "priority": 2,
  "issue_type": "bug",
  "owner": "mark@wolfssl.com",
  "created_at": "2026-04-20T05:11:45Z",
  "created_by": "Mark Atwood",
  "updated_at": "2026-04-20T05:20:16Z",
  "closed_at": "2026-04-20T05:20:16Z",
  "close_reason": "Closed",
  "dependencies": [
    {
      "dep_type": "parent_child",
      "created_by": "Mark Atwood",
      "created_at": "2026-04-19T22:11:45Z"
    }
  ]
}
