{
  "id": "nie-0j6b.5",
  "title": "blob download: stored content-type reflected without sanitization",
  "description": "handle_jmap_upload stores the raw client-supplied Content-Type header in the blob table (no parsing, no allowlist). handle_jmap_download returns it as the response Content-Type header. A caller can upload with Content-Type: text/html and the blob download endpoint will serve it with that type. This is already tracked as nie-po5v.3 (XSS) but the correctness angle is different: if a client uploads with a malformed content-type (e.g. containing newlines), the raw bytes reach axum's header serializer, which may panic or produce a malformed HTTP response. Trigger: upload with Content-Type containing CRLF characters.",
  "status": "closed",
  "priority": 0,
  "issue_type": "bug",
  "owner": "mark@reviewcommit.com",
  "created_at": "2026-04-25T03:54:54Z",
  "created_by": "Mark Atwood",
  "updated_at": "2026-04-26T06:36:59Z",
  "closed_at": "2026-04-26T06:36:59Z",
  "close_reason": "Closed",
  "labels": [
    "correctness",
    "my-oss",
    "review"
  ],
  "dependencies": [
    {
      "dep_type": "parent_child",
      "created_by": "Mark Atwood",
      "created_at": "2026-04-24 20:54:54"
    }
  ]
}
